{"login": "Vamei", "id": 1069643, "node_id": "MDQ6VXNlcjEwNjk2NDM=", "avatar_url": "https://avatars.githubusercontent.com/u/1069643?v=4", "gravatar_id": "", "url": "https://api.github.com/users/Vamei", "html_url": "https://github.com/Vamei", "followers_url": "https://api.github.com/users/Vamei/followers", "following_url": "https://api.github.com/users/Vamei/following{/other_user}", "gists_url": "https://api.github.com/users/Vamei/gists{/gist_id}", "starred_url": "https://api.github.com/users/Vamei/starred{/owner}{/repo}", "subscriptions_url": "https://api.github.com/users/Vamei/subscriptions", "organizations_url": "https://api.github.com/users/Vamei/orgs", "repos_url": "https://api.github.com/users/Vamei/repos", "events_url": "https://api.github.com/users/Vamei/events{/privacy}", "received_events_url": "https://api.github.com/users/Vamei/received_events", "type": "User", "user_view_type": "public", "site_admin": false, "name": "Vamei", "company": null, "blog": "http://www.cnblogs.com/vamei", "location": "Singapore, Shanghai", "email": "ztftom@gmail.com", "hireable": null, "bio": null, "twitter_username": null, "public_repos": 15, "public_gists": 0, "followers": 2167, "following": 6, "created_at": "2011-09-22T01:39:03Z", "updated_at": "2018-07-04T03:35:26Z"}