{"login": "okx", "id": 120148534, "node_id": "O_kgDOBylSNg", "avatar_url": "https://avatars.githubusercontent.com/u/120148534?v=4", "gravatar_id": "", "url": "https://api.github.com/users/okx", "html_url": "https://github.com/okx", "followers_url": "https://api.github.com/users/okx/followers", "following_url": "https://api.github.com/users/okx/following{/other_user}", "gists_url": "https://api.github.com/users/okx/gists{/gist_id}", "starred_url": "https://api.github.com/users/okx/starred{/owner}{/repo}", "subscriptions_url": "https://api.github.com/users/okx/subscriptions", "organizations_url": "https://api.github.com/users/okx/orgs", "repos_url": "https://api.github.com/users/okx/repos", "events_url": "https://api.github.com/users/okx/events{/privacy}", "received_events_url": "https://api.github.com/users/okx/received_events", "type": "Organization", "user_view_type": "public", "site_admin": false, "name": "OKX.com", "company": null, "blog": "https://www.okx.com", "location": "Singapore", "email": "support@okx.com", "hireable": null, "bio": "OKX is a world-leading digital asset exchange, providing advanced financial services to traders globally by using blockchain technology.", "twitter_username": null, "public_repos": 132, "public_gists": 0, "followers": 1154, "following": 0, "created_at": "2022-12-09T01:40:23Z", "updated_at": "2022-12-14T03:27:19Z"}