{"login": "yjsoon", "id": 126824, "node_id": "MDQ6VXNlcjEyNjgyNA==", "avatar_url": "https://avatars.githubusercontent.com/u/126824?v=4", "gravatar_id": "", "url": "https://api.github.com/users/yjsoon", "html_url": "https://github.com/yjsoon", "followers_url": "https://api.github.com/users/yjsoon/followers", "following_url": "https://api.github.com/users/yjsoon/following{/other_user}", "gists_url": "https://api.github.com/users/yjsoon/gists{/gist_id}", "starred_url": "https://api.github.com/users/yjsoon/starred{/owner}{/repo}", "subscriptions_url": "https://api.github.com/users/yjsoon/subscriptions", "organizations_url": "https://api.github.com/users/yjsoon/orgs", "repos_url": "https://api.github.com/users/yjsoon/repos", "events_url": "https://api.github.com/users/yjsoon/events{/privacy}", "received_events_url": "https://api.github.com/users/yjsoon/received_events", "type": "User", "user_view_type": "public", "site_admin": false, "name": "YJ Soon", "company": "Tinkertanker", "blog": "http://tinkercademy.com", "location": "Singapore", "email": "yjsoon@tinkertanker.com", "hireable": null, "bio": null, "twitter_username": null, "public_repos": 123, "public_gists": 26, "followers": 104, "following": 24, "created_at": "2009-09-14T16:35:45Z", "updated_at": "2024-10-10T01:52:14Z"}