{"login": "DonChiaQE", "id": 24926784, "node_id": "MDQ6VXNlcjI0OTI2Nzg0", "avatar_url": "https://avatars.githubusercontent.com/u/24926784?v=4", "gravatar_id": "", "url": "https://api.github.com/users/DonChiaQE", "html_url": "https://github.com/DonChiaQE", "followers_url": "https://api.github.com/users/DonChiaQE/followers", "following_url": "https://api.github.com/users/DonChiaQE/following{/other_user}", "gists_url": "https://api.github.com/users/DonChiaQE/gists{/gist_id}", "starred_url": "https://api.github.com/users/DonChiaQE/starred{/owner}{/repo}", "subscriptions_url": "https://api.github.com/users/DonChiaQE/subscriptions", "organizations_url": "https://api.github.com/users/DonChiaQE/orgs", "repos_url": "https://api.github.com/users/DonChiaQE/repos", "events_url": "https://api.github.com/users/DonChiaQE/events{/privacy}", "received_events_url": "https://api.github.com/users/DonChiaQE/received_events", "type": "User", "user_view_type": "public", "site_admin": false, "name": "lizardon", "company": "@nossaflex", "blog": "donchia.tech", "location": "Singapore", "email": null, "hireable": null, "bio": "Indie App & Web Developer | \r\n2x Apple WWDC Scholar ('21 & '22) \ud83c\udf93\r\n\r\nFrontend developer by day, Backend developer by night", "twitter_username": "lizarDON2303", "public_repos": 37, "public_gists": 5, "followers": 113, "following": 63, "created_at": "2017-01-05T01:04:55Z", "updated_at": "2024-10-13T11:31:14Z"}