{"login": "BugenZhao", "id": 25862682, "node_id": "MDQ6VXNlcjI1ODYyNjgy", "avatar_url": "https://avatars.githubusercontent.com/u/25862682?v=4", "gravatar_id": "", "url": "https://api.github.com/users/BugenZhao", "html_url": "https://github.com/BugenZhao", "followers_url": "https://api.github.com/users/BugenZhao/followers", "following_url": "https://api.github.com/users/BugenZhao/following{/other_user}", "gists_url": "https://api.github.com/users/BugenZhao/gists{/gist_id}", "starred_url": "https://api.github.com/users/BugenZhao/starred{/owner}{/repo}", "subscriptions_url": "https://api.github.com/users/BugenZhao/subscriptions", "organizations_url": "https://api.github.com/users/BugenZhao/orgs", "repos_url": "https://api.github.com/users/BugenZhao/repos", "events_url": "https://api.github.com/users/BugenZhao/events{/privacy}", "received_events_url": "https://api.github.com/users/BugenZhao/received_events", "type": "User", "user_view_type": "public", "site_admin": false, "name": "Bugen Zhao", "company": "@risingwavelabs", "blog": "bugenzhao.com", "location": "Singapore", "email": "i@bugenzhao.com", "hireable": null, "bio": "database engineer @risingwavelabs, bachelor @SJTU-CSE, created MNGA App", "twitter_username": "BugenZhao", "public_repos": 95, "public_gists": 9, "followers": 578, "following": 157, "created_at": "2017-02-18T10:40:53Z", "updated_at": "2024-10-17T02:36:46Z"}