{"login": "CMGS", "id": 506216, "node_id": "MDQ6VXNlcjUwNjIxNg==", "avatar_url": "https://avatars.githubusercontent.com/u/506216?v=4", "gravatar_id": "", "url": "https://api.github.com/users/CMGS", "html_url": "https://github.com/CMGS", "followers_url": "https://api.github.com/users/CMGS/followers", "following_url": "https://api.github.com/users/CMGS/following{/other_user}", "gists_url": "https://api.github.com/users/CMGS/gists{/gist_id}", "starred_url": "https://api.github.com/users/CMGS/starred{/owner}{/repo}", "subscriptions_url": "https://api.github.com/users/CMGS/subscriptions", "organizations_url": "https://api.github.com/users/CMGS/orgs", "repos_url": "https://api.github.com/users/CMGS/repos", "events_url": "https://api.github.com/users/CMGS/events{/privacy}", "received_events_url": "https://api.github.com/users/CMGS/received_events", "type": "User", "user_view_type": "public", "site_admin": false, "name": "CMGS", "company": null, "blog": "http://cmgs.me", "location": "Singapore", "email": "ilskdw@gmail.com", "hireable": null, "bio": "Ghost like", "twitter_username": null, "public_repos": 66, "public_gists": 22, "followers": 984, "following": 29, "created_at": "2010-12-02T07:28:41Z", "updated_at": "2024-10-16T12:41:09Z"}