{"login": "sogko", "id": 78585, "node_id": "MDQ6VXNlcjc4NTg1", "avatar_url": "https://avatars.githubusercontent.com/u/78585?v=4", "gravatar_id": "", "url": "https://api.github.com/users/sogko", "html_url": "https://github.com/sogko", "followers_url": "https://api.github.com/users/sogko/followers", "following_url": "https://api.github.com/users/sogko/following{/other_user}", "gists_url": "https://api.github.com/users/sogko/gists{/gist_id}", "starred_url": "https://api.github.com/users/sogko/starred{/owner}{/repo}", "subscriptions_url": "https://api.github.com/users/sogko/subscriptions", "organizations_url": "https://api.github.com/users/sogko/orgs", "repos_url": "https://api.github.com/users/sogko/repos", "events_url": "https://api.github.com/users/sogko/events{/privacy}", "received_events_url": "https://api.github.com/users/sogko/received_events", "type": "User", "user_view_type": "public", "site_admin": false, "name": "Hafiz Ismail", "company": null, "blog": "https://wehavefaces.net", "location": "Singapore", "email": null, "hireable": null, "bio": "software engineer | open-source buccaneer | aphrostysicist", "twitter_username": null, "public_repos": 92, "public_gists": 26, "followers": 309, "following": 26, "created_at": "2009-04-28T01:50:43Z", "updated_at": "2024-04-04T03:01:50Z"}