{"login": "toeverything", "id": 78728988, "node_id": "MDEyOk9yZ2FuaXphdGlvbjc4NzI4OTg4", "avatar_url": "https://avatars.githubusercontent.com/u/78728988?v=4", "gravatar_id": "", "url": "https://api.github.com/users/toeverything", "html_url": "https://github.com/toeverything", "followers_url": "https://api.github.com/users/toeverything/followers", "following_url": "https://api.github.com/users/toeverything/following{/other_user}", "gists_url": "https://api.github.com/users/toeverything/gists{/gist_id}", "starred_url": "https://api.github.com/users/toeverything/starred{/owner}{/repo}", "subscriptions_url": "https://api.github.com/users/toeverything/subscriptions", "organizations_url": "https://api.github.com/users/toeverything/orgs", "repos_url": "https://api.github.com/users/toeverything/repos", "events_url": "https://api.github.com/users/toeverything/events{/privacy}", "received_events_url": "https://api.github.com/users/toeverything/received_events", "type": "Organization", "user_view_type": "public", "site_admin": false, "name": "Toeverything", "company": null, "blog": "", "location": "Singapore", "email": "developer@affine.pro", "hireable": null, "bio": "Building for a semantic future. To shape, not to adapt. https://affine.pro", "twitter_username": "AffineOfficial", "public_repos": 40, "public_gists": 0, "followers": 1040, "following": 0, "created_at": "2021-02-08T09:54:14Z", "updated_at": "2024-10-24T17:21:58Z"}